[{"vehicle": "Vehicle 0", "listtime": [590, 473, 435, 382, 408], "rute": [[0, 5], [5, 12], [12, 3], [3, 6], [6, 0]], "time_window": ["0 --- 5000", "325 --- 1525", "140 --- 1340", "1129 --- 2329", "810 --- 2010"], "leading": [0, 0, 0, 0, 0], "delay": [0, 0, 158, 0, 278], "step": [590, 1063, 1498, 1880, 2288], "time": 2288}, {"vehicle": "Vehicle 1", "listtime": [440, 320, 357, 356, 279, 366, 415], "rute": [[0, 9], [9, 2], [2, 8], [8, 14], [14, 13], [13, 11], [11, 0]], "time_window": ["0 --- 5000", "605 --- 1805", "367 --- 1567", "860 --- 2060", "1018 --- 2218", "687 --- 1887", "1078 --- 2278"], "leading": [0, 0, 0, 0, 0, 0, 0], "delay": [0, 0, 0, 0, 0, 231, 255], "step": [440, 760, 1117, 1473, 1752, 2118, 2533], "time": 2533}, {"vehicle": "Vehicle 2", "listtime": [563, 339, 459, 403, 421, 593], "rute": [[0, 15], [15, 4], [4, 7], [7, 1], [1, 10], [10, 0]], "time_window": ["0 --- 5000", "576 --- 1776", "202 --- 1402", "219 --- 1419", "987 --- 2187", "117 --- 1317"], "leading": [0, 0, 0, 0, 0, 0], "delay": [0, 0, 0, 345, 0, 1461], "step": [563, 902, 1361, 1764, 2185, 2778], "time": 2778}]